suftware/__init__.py
suftware/_version.py
suftware/deft_core.py
suftware/density.py
suftware/density_estimator.py
suftware/example_dataset.py
suftware/examples/data/buffalo_snowfall.txt
suftware/examples/data/old_faithful_eruption_times.txt
suftware/examples/data/old_faithful_waiting_times.txt
suftware/examples/data/treatment_length.txt
suftware/examples/data/who.adolescent_births.txt
suftware/examples/data/who.air_pollution_mortality.txt
suftware/examples/data/who.alcohol_consumption.txt
suftware/examples/data/who.attended_births.txt
suftware/examples/data/who.cause_of_death_known.txt
suftware/examples/data/who.child_overweight.txt
suftware/examples/data/who.child_stunting.txt
suftware/examples/data/who.child_wasting.txt
suftware/examples/data/who.clean_fuels.txt
suftware/examples/data/who.clean_water.txt
suftware/examples/data/who.conflict_deaths.txt
suftware/examples/data/who.dpt_immunization.txt
suftware/examples/data/who.early_disease_deaths.txt
suftware/examples/data/who.family_planning.txt
suftware/examples/data/who.govt_expendature.txt
suftware/examples/data/who.health_and_research.txt
suftware/examples/data/who.health_professionals.txt
suftware/examples/data/who.hepatitis_vaccine.txt
suftware/examples/data/who.hiv_infections.txt
suftware/examples/data/who.homicide.txt
suftware/examples/data/who.life_expectancy.txt
suftware/examples/data/who.life_expectancy_female.txt
suftware/examples/data/who.life_expectancy_healthy.txt
suftware/examples/data/who.life_expectancy_male.txt
suftware/examples/data/who.malaria_incidence.txt
suftware/examples/data/who.maternal_mortality.txt
suftware/examples/data/who.natural_disasters.txt
suftware/examples/data/who.neonatal_moratlity.txt
suftware/examples/data/who.ntd_interventions.txt
suftware/examples/data/who.particulate_matter.txt
suftware/examples/data/who.poisoning_mortality.txt
suftware/examples/data/who.population.txt
suftware/examples/data/who.sanitation.txt
suftware/examples/data/who.score_avg.txt
suftware-1.0.4.dist-info/LICENSE
suftware-1.0.4.dist-info/METADATA
suftware-1.0.4.dist-info/WHEEL
suftware-1.0.4.dist-info/RECORD
