Metadata-Version: 2.1
Name: suftware
Version: 1.0.4
Summary: One-dimensional density estimation using Bayesian field theory.
License: MIT
Author: Justin B. Kinney
Author-email: jkinney@cshl.edu
Requires-Python: >=3.10
Classifier: License :: OSI Approved :: MIT License
Classifier: Programming Language :: Python :: 3
Classifier: Programming Language :: Python :: 3.10
Classifier: Programming Language :: Python :: 3.11
Classifier: Programming Language :: Python :: 3.12
Classifier: Programming Language :: Python :: 3.13
Requires-Dist: matplotlib (>=3.3.0)
Requires-Dist: numpy (>=1.26.0)
Requires-Dist: numpydoc (>=0.8.0)
Requires-Dist: pandas (>=1.2.0)
Requires-Dist: scipy (>=1.5.0)
Requires-Dist: sphinx (>=7.0.0)
Requires-Dist: sphinx-rtd-theme (>=1.3.0)
